waltzboard/__about__.py
waltzboard/__init__.py
waltzboard/app.py
waltzboard/config.py
waltzboard/utills.py
waltzboard/waltzboard.py
waltzboard/api/routers/__init__.py
waltzboard/api/routers/get_chart.py
waltzboard/api/routers/infer.py
waltzboard/api/routers/init.py
waltzboard/api/routers/inspect.py
waltzboard/api/routers/is_valid.py
waltzboard/api/routers/recommends.py
waltzboard/api/routers/score.py
waltzboard/api/routers/train.py
waltzboard/api/routers/variants.py
waltzboard/api/static/index.html
waltzboard/api/static/assets/PretendardVariable-a623dbe9.woff2
waltzboard/api/static/assets/index-0a3cb5d5.css
waltzboard/api/static/assets/index-1f957121.js
waltzboard/api/static/assets/rajdhani-devanagari-400-normal-6f7e418f.woff2
waltzboard/api/static/assets/rajdhani-devanagari-400-normal-cdf9476b.woff
waltzboard/api/static/assets/rajdhani-latin-400-normal-759a9000.woff2
waltzboard/api/static/assets/rajdhani-latin-400-normal-fe445fb9.woff
waltzboard/api/static/assets/rajdhani-latin-ext-400-normal-45ce7273.woff
waltzboard/api/static/assets/rajdhani-latin-ext-400-normal-dbf5014d.woff2
waltzboard/explorer/__init__.py
waltzboard/explorer/explorer.py
waltzboard/explorer/explorer_config.py
waltzboard/explorer/explorer_result.py
waltzboard/generator/__init__.py
waltzboard/generator/generator.py
waltzboard/generator/generator_parameters.py
waltzboard/model/__init__.py
waltzboard/model/attribute.py
waltzboard/model/chart_map.py
waltzboard/model/const.py
waltzboard/model/waltzboard_chart.py
waltzboard/model/waltzboard_dahsboard.py
waltzboard/model/charts/__init__.py
waltzboard/model/charts/bar_chart.py
waltzboard/model/charts/base_chart.py
waltzboard/model/charts/box_plot.py
waltzboard/model/charts/heatmap.py
waltzboard/model/charts/line_chart.py
waltzboard/model/charts/pie_chart.py
waltzboard/model/charts/scatter_plot.py
waltzboard/model/charts/strip_plot.py
waltzboard/oracle/__init__.py
waltzboard/oracle/oracle.py
waltzboard/oracle/oracle_result.py
waltzboard-1.0.0a0.dist-info/METADATA
waltzboard-1.0.0a0.dist-info/WHEEL
waltzboard-1.0.0a0.dist-info/licenses/LICENSE
waltzboard-1.0.0a0.dist-info/RECORD
