Metadata-Version: 2.1
Name: waltzboard
Version: 1.0.0a0
Summary: Waltzboard: Multi-Criteria Automated Dashboard Design
Project-URL: Documentation, https://github.com/jiwnchoi/Waltzboard#readme
Project-URL: Issues, https://github.com/jiwnchoi/Waltzboard/issues
Project-URL: Source, https://github.com/jiwnchoi/Waltzboard
Author-email: Jiwon Choi <jiwnchoi@skku.edu>, Jaemin Jo <jmjo@skku.edu>
License-Expression: MIT
License-File: LICENSE
Classifier: Development Status :: 4 - Beta
Classifier: Programming Language :: Python
Classifier: Programming Language :: Python :: 3.9
Classifier: Programming Language :: Python :: 3.10
Classifier: Programming Language :: Python :: 3.11
Classifier: Programming Language :: Python :: 3.12
Classifier: Programming Language :: Python :: Implementation :: CPython
Classifier: Programming Language :: Python :: Implementation :: PyPy
Requires-Python: >=3.9
Requires-Dist: altair
Requires-Dist: fastapi
Requires-Dist: ipython
Requires-Dist: numpy
Requires-Dist: pandas
Requires-Dist: pydantic-settings
Requires-Dist: scikit-learn
Requires-Dist: uvicorn
